Metadata-Version: 2.1
Name: eelJINJAenv
Version: 0.15.4
Summary: For little HTML GUI applications, with easy Python/JS interop
Home-page: https://github.com/forno96/Eel
Author: Chris Knott, Francesco Fornari
Author-email: francesco.fornari.96@gmail.com
License: UNKNOWN
Keywords: gui,html,javascript,electron
Platform: UNKNOWN
Classifier: Development Status :: 3 - Alpha
Classifier: Natural Language :: English
Classifier: Operating System :: MacOS
Classifier: Operating System :: POSIX
Classifier: Operating System :: Microsoft :: Windows :: Windows 10
Classifier: Programming Language :: Python :: 3
Classifier: Programming Language :: Python :: 3.6
Classifier: Programming Language :: Python :: 3.7
Classifier: Programming Language :: Python :: 3.8
Classifier: Programming Language :: Python :: Implementation :: CPython
Classifier: License :: OSI Approved :: MIT License
Requires-Python: >=3.6
